{
  "visible": true,
  "offset_x": -0.317,
  "offset_y": -0.1805,
  "offset_z": 0.01,
  "Comparer": {},
  "Count": 2,
  "Keys": [
    0,
    1
  ],
  "Values": [
    {
      "Vertices": [
        0.634,
        0.0,
        0.0,
        0.24,
        1.0,
        0.24,
        0.634,
        0.381,
        0.0,
        1.0,
        0.24,
        0.24,
        0.0,
        0.0,
        0.0,
        0.24,
        0.24,
        1.0
      ]
    },
    {
      "Vertices": [
        0.634,
        0.381,
        0.0,
        1.0,
        0.24,
        0.24,
        0.0,
        -0.0,
        0.0,
        0.24,
        0.24,
        1.0,
        0.0,
        0.381,
        0.0,
        0.24,
        0.24,
        0.24
      ]
    }
  ]
}